collective/elastic/plone/__init__.py
collective/elastic/plone/configure.zcml
collective/elastic/plone/interfaces.py
collective/elastic/plone/proxyindex.py
collective/elastic/plone/queueprocessor.py
collective/elastic/plone/setuphandlers.py
collective/elastic/plone/testing.py
collective/elastic/plone/upgrades.py
collective/elastic/plone/upgrades.zcml
collective/elastic/plone/browser/__init__.py
collective/elastic/plone/browser/configure.zcml
collective/elastic/plone/browser/update.py
collective/elastic/plone/browser/static/.gitkeep
collective/elastic/plone/locales/README.rst
collective/elastic/plone/locales/__init__.py
collective/elastic/plone/locales/collective.es.plone.pot
collective/elastic/plone/locales/update.py
collective/elastic/plone/locales/update.sh
collective/elastic/plone/locales/en/LC_MESSAGES/collective.es.plone.po
collective/elastic/plone/profiles/default/browserlayer.xml
collective/elastic/plone/profiles/default/catalog.xml
collective/elastic/plone/profiles/default/metadata.xml
collective/elastic/plone/profiles/uninstall/browserlayer.xml
collective/elastic/plone/profiles/uninstall/catalog.xml
collective/elastic/plone/restapi/__init__.py
collective/elastic/plone/restapi/blocks.py
collective/elastic/plone/restapi/configure.zcml
collective/elastic/plone/restapi/expansions.py
collective/elastic/plone/restapi/schema.py
collective/elastic/plone/restapi/service.py
collective/elastic/plone/restapi/kitsearch/__init__.py
collective/elastic/plone/restapi/kitsearch/configure.zcml
collective/elastic/plone/restapi/kitsearch/post.py
collective/elastic/plone/restapi/kitsearch/request_example.json
collective/elastic/plone/restapi/kitsearch/response_example.json
collective/elastic/plone/www/addIndex.zpt
collective/elastic/plone/www/index.gif
collective/elastic/plone/www/manageIndex.zpt
collective.elastic.plone-2.1.1.dist-info/LICENSE.GPL
collective.elastic.plone-2.1.1.dist-info/LICENSE.rst
collective.elastic.plone-2.1.1.dist-info/METADATA
collective.elastic.plone-2.1.1.dist-info/WHEEL
collective.elastic.plone-2.1.1.dist-info/top_level.txt
collective.elastic.plone-2.1.1.dist-info/RECORD
