Metadata-Version: 2.1
Name: collective.elastic.plone
Version: 2.1.1
Summary: Plone Search Integration: Addon to index content in Open-/ElasticSearch
Author: Jens Klein, Katja Süss, Peter Holzer
Maintainer-email: Jens Klein <jk@kleinundpartner.at>
License: GPL 2.0
Project-URL: PyPI, https://pypi.python.org/pypi/collective.elastic.plone
Project-URL: Changelog, https://github.com/collective/collective.elastic.plone/blob/main/CHANGES.rst
Project-URL: Source, https://github.com/collective/collective.elastic.plone
Project-URL: Issues, https://github.com/collective/collective.elastic.plone/issues
Keywords: elasticsearch,opensearch,plone,celery,search,indexer
Classifier: Environment :: Web Environment
Classifier: Framework :: Plone
Classifier: Framework :: Plone :: Addon
Classifier: Framework :: Plone :: 6.0
Classifier: Framework :: Plone :: 6.1
Classifier: Programming Language :: Python
Classifier: Programming Language :: Python :: 3.9
Classifier: Programming Language :: Python :: 3.10
Classifier: Programming Language :: Python :: 3.11
Classifier: Programming Language :: Python :: 3.12
Classifier: Operating System :: OS Independent
Classifier: License :: OSI Approved :: GNU General Public License v2 (GPLv2)
Classifier: Development Status :: 5 - Production/Stable
Requires-Python: >=3.9
License-File: LICENSE.GPL
License-File: LICENSE.rst
Requires-Dist: plone.restapi
Requires-Dist: collective.elastic.ingest >=2.1.0
Requires-Dist: jinja2
Requires-Dist: deepmerge
Provides-Extra: elasticsearch
Requires-Dist: collective.elastic.ingest[elasticsearch] ; extra == 'elasticsearch'
Provides-Extra: opensearch
Requires-Dist: collective.elastic.ingest[opensearch] ; extra == 'opensearch'
Provides-Extra: rabbitmq
Requires-Dist: collective.elastic.ingest[rabbitmq] ; extra == 'rabbitmq'
Provides-Extra: redis
Requires-Dist: collective.elastic.ingest[redis] ; extra == 'redis'
Provides-Extra: sentry
Requires-Dist: sentry-sdk ; extra == 'sentry'
Provides-Extra: test
Requires-Dist: plone.app.contenttypes[test] ; extra == 'test'
Requires-Dist: pytest-plone ; extra == 'test'
Requires-Dist: pdbpp ; extra == 'test'
